nonebot_plugin_jrrp3/__init__.py
nonebot_plugin_jrrp3/command.py
nonebot_plugin_jrrp3/config.py
nonebot_plugin_jrrp3/constants.py
nonebot_plugin_jrrp3/database.py
nonebot_plugin_jrrp3/utils.py
nonebot_plugin_jrrp3-3.4.0.dist-info/METADATA
nonebot_plugin_jrrp3-3.4.0.dist-info/WHEEL
nonebot_plugin_jrrp3-3.4.0.dist-info/licenses/LICENSE
nonebot_plugin_jrrp3-3.4.0.dist-info/RECORD
