Metadata-Version: 2.4
Name: nonebot-plugin-jrrp3
Version: 3.4.0
Summary: 更加现代化的 NoneBot2 每日人品插件，支持查询今日、本周、本月和历史平均人品，自定义运势，以及数据持久化存储。
License-File: LICENSE
Author: GT610
Author-email: myddz1005@outlook.com
Requires-Python: >=3.9,<4.0
Classifier: Programming Language :: Python :: 3
Classifier: Programming Language :: Python :: 3.9
Classifier: Programming Language :: Python :: 3.10
Classifier: Programming Language :: Python :: 3.11
Classifier: Programming Language :: Python :: 3.12
Classifier: Programming Language :: Python :: 3.13
Classifier: Programming Language :: Python :: 3.14
Requires-Dist: nonebot-plugin-alconna (>=0.50.0)
Requires-Dist: nonebot-plugin-localstore (>=0.6.0)
Requires-Dist: nonebot2 (>=2.3.0,<3.0.0)
Requires-Dist: pyyaml (>=6.0)
